build/lib/fluss_api/__init__.py
build/lib/fluss_api/main.py
fluss_api/__init__.py
fluss_api/main.py
fluss_api-0.1.9.20.dist-info/licenses/LICENSE
fluss_api-0.1.9.20.dist-info/METADATA
fluss_api-0.1.9.20.dist-info/WHEEL
fluss_api-0.1.9.20.dist-info/top_level.txt
fluss_api-0.1.9.20.dist-info/RECORD
